CHANGES.rst
LICENSE.txt
MANIFEST.in
NOTICE.txt
README.rst
REFERENCES.txt
setup.py
PyAlgDat.egg-info/PKG-INFO
PyAlgDat.egg-info/SOURCES.txt
PyAlgDat.egg-info/dependency_links.txt
PyAlgDat.egg-info/not-zip-safe
PyAlgDat.egg-info/requires.txt
PyAlgDat.egg-info/top_level.txt
docs/__init__.py
examples/.DS_Store
examples/__init__.py
examples/depth_first_graph_test.py
examples/dijkstra_test.py
examples/kruskal_test.py
examples/prim_test.py
examples/shortest_path_test.py
py_alg_dat/__init__.py
py_alg_dat/array_list.py
py_alg_dat/association.py
py_alg_dat/binary_heap.py
py_alg_dat/container.py
py_alg_dat/dfs_edge_classification.py
py_alg_dat/doubly_linked_list.py
py_alg_dat/entry.py
py_alg_dat/graph.py
py_alg_dat/graph_algorithms.py
py_alg_dat/graph_edge.py
py_alg_dat/graph_path.py
py_alg_dat/graph_vertex.py
py_alg_dat/graph_visitor.py
py_alg_dat/iterator.py
py_alg_dat/linked_list.py
py_alg_dat/linked_list_iterator.py
py_alg_dat/max_heap.py
py_alg_dat/min_heap.py
py_alg_dat/minimum_spanning_tree.py
py_alg_dat/partition.py
py_alg_dat/queue.py
py_alg_dat/singly_linked_list.py
py_alg_dat/stack.py
py_alg_dat/string_visitor.py
py_alg_dat/vertex_visitor.py
py_alg_dat/visitor.py
testsuite/__init__.py
testsuite/__init__.pyc
testsuite/test_array_list.py
testsuite/test_array_list.pyc
testsuite/test_association.py
testsuite/test_association.pyc
testsuite/test_container.py
testsuite/test_container.pyc
testsuite/test_dfs_edge_classification.py
testsuite/test_dfs_edge_classification.pyc
testsuite/test_directed_graph.py
testsuite/test_directed_graph.pyc
testsuite/test_directed_un_weighted_graph.py
testsuite/test_directed_un_weighted_graph.pyc
testsuite/test_directed_weighted_graph.py
testsuite/test_directed_weighted_graph.pyc
testsuite/test_doubly_linked_list.py
testsuite/test_doubly_linked_list.pyc
testsuite/test_entry.py
testsuite/test_entry.pyc
testsuite/test_graph_algorithms.py
testsuite/test_graph_algorithms.pyc
testsuite/test_graph_algorithms.py~
testsuite/test_graph_edge.py
testsuite/test_graph_edge.pyc
testsuite/test_graph_vertex.py
testsuite/test_graph_vertex.pyc
testsuite/test_max_heap.py
testsuite/test_max_heap.pyc
testsuite/test_max_heap.py~
