Metadata-Version: 1.1
Name: PyAlgDat
Version: 1.0.2
Summary: Various data structures and algorithms.
Home-page: http://www.brianhorn.dk
Author: Brian Horn
Author-email: trycatchhorn@gmail.com
License: The MIT License (MIT)
